bleurt_pytorch/__init__.py
bleurt_pytorch/bleurt/__init__.py
bleurt_pytorch/bleurt/configuration_bleurt.py
bleurt_pytorch/bleurt/modeling_bleurt.py
bleurt_pytorch/bleurt/tokenization_bleurt.py
bleurt_pytorch/bleurt/tokenization_bleurt_fast.py
bleurt_pytorch/bleurt/tokenization_bleurt_sp.py
bleurt_pytorch/utils/__init__.py
bleurt_pytorch/utils/convert_tf_to_pytorch_bleurt.py
bleurt_pytorch-0.0.1.dist-info/LICENSE
bleurt_pytorch-0.0.1.dist-info/METADATA
bleurt_pytorch-0.0.1.dist-info/WHEEL
bleurt_pytorch-0.0.1.dist-info/top_level.txt
bleurt_pytorch-0.0.1.dist-info/RECORD
