Metadata-Version: 2.1
Name: bleurt-pytorch
Version: 0.0.1
Summary: PyTorch porting of BLEURT
Home-page: https://github.com/lucadiliello/bleurt_pytorch.git
Author: Luca Di Liello
Author-email: luca.diliello@unitn.it
License: Apache License Version 2.0
Classifier: Programming Language :: Python :: 3
Classifier: License :: OSI Approved :: Apache Software License
Classifier: Operating System :: OS Independent
License-File: LICENSE
Requires-Dist: torch >=1.10
Requires-Dist: transformers >=4.25
Requires-Dist: sentencepiece >=0.1.97
